LICENSE
MANIFEST.in
README.md
setup.py
./.gitlab-ci.yml
./pyPhasesRecordloaderMESA/config.yaml
pyPhasesRecordloaderMESA/Plugin.py
pyPhasesRecordloaderMESA/__init__.py
pyPhasesRecordloaderMESA/config.yaml
pyPhasesRecordloaderMESA.egg-info/PKG-INFO
pyPhasesRecordloaderMESA.egg-info/SOURCES.txt
pyPhasesRecordloaderMESA.egg-info/dependency_links.txt
pyPhasesRecordloaderMESA.egg-info/requires.txt
pyPhasesRecordloaderMESA.egg-info/top_level.txt
pyPhasesRecordloaderMESA/recordLoaders/MESAAnnotationLoader.py
pyPhasesRecordloaderMESA/recordLoaders/RecordLoaderMESA.py
pyPhasesRecordloaderMESA/recordLoaders/__init__.py